air/__init__.py
air/__main__.py
air/applications.py
air/background.py
air/cli.py
air/dependencies.py
air/exception_handlers.py
air/exceptions.py
air/forms.py
air/layouts.py
air/middleware.py
air/models.py
air/py.typed
air/requests.py
air/responses.py
air/routing.py
air/tags/__init__.py
air/tags/constants.py
air/tags/models/__init__.py
air/tags/models/base.py
air/tags/models/special.py
air/tags/models/stock.py
air/tags/models/svg.py
air/tags/models/types.py
air/tags/models/utils.py
air/tags/types.py
air/tags/utils.py
air/templating.py
air/types.py
air/utils.py
air-0.45.0.dist-info/WHEEL
air-0.45.0.dist-info/entry_points.txt
air-0.45.0.dist-info/METADATA
air-0.45.0.dist-info/RECORD
