Metadata-Version: 2.3
Name: air
Version: 0.45.0
Summary: The new Python web framework by the authors of Two Scoops of Django. Built with FastAPI, Starlette, and Pydantic.
Keywords: air,air-tags,api,async,backend,css,fastapi,fasthtml,framework,frontend,fullstack,html,javascript,jinja,jinja2,openapi,pydantic,python,rest,restapi,restful,server,templates,uvicorn,web
Author: Audrey M. Roy Greenfeld, Daniel Roy Greenfeld
Author-email: Audrey M. Roy Greenfeld <audrey@feldroy.com>, Daniel Roy Greenfeld <daniel@feldroy.com>
License: MIT License
Classifier: Development Status :: 3 - Alpha
Classifier: Environment :: Web Environment
Classifier: Framework :: FastAPI
Classifier: Framework :: Pydantic
Classifier: Framework :: Pydantic :: 2
Classifier: Intended Audience :: Developers
Classifier: License :: OSI Approved :: MIT License
Classifier: Natural Language :: English
Classifier: Operating System :: MacOS
Classifier: Operating System :: Microsoft :: Windows
Classifier: Operating System :: OS Independent
Classifier: Operating System :: Unix
Classifier: Programming Language :: JavaScript
Classifier: Programming Language :: Python
Classifier: Programming Language :: Python :: 3
Classifier: Programming Language :: Python :: 3 :: Only
Classifier: Programming Language :: Python :: 3.13
Classifier: Programming Language :: Python :: 3.14
Classifier: Programming Language :: Python :: Implementation :: CPython
Classifier: Topic :: Internet
Classifier: Topic :: Internet :: WWW/HTTP
Classifier: Topic :: Internet :: WWW/HTTP :: HTTP Servers
Classifier: Topic :: Internet :: WWW/HTTP :: WSGI
Classifier: Topic :: Internet :: WWW/HTTP :: WSGI :: Application
Classifier: Topic :: Internet :: WWW/HTTP :: WSGI :: Middleware
Classifier: Topic :: Internet :: WWW/HTTP :: WSGI :: Server
Classifier: Topic :: Software Development
Classifier: Topic :: Software Development :: Libraries
Classifier: Topic :: Software Development :: Libraries :: Application Frameworks
Classifier: Topic :: Software Development :: Libraries :: Python Modules
Classifier: Topic :: Text Processing
Classifier: Topic :: Text Processing :: Markup
Classifier: Topic :: Text Processing :: Markup :: HTML
Classifier: Typing :: Typed
Requires-Dist: jinja2>=3.1.6
Requires-Dist: fastapi>=0.125.0
Requires-Dist: frozendict>=2.4.7
Requires-Dist: itsdangerous>=2.2.0
Requires-Dist: lxml>=6.0.1
Requires-Dist: minify-html>=0.18.1
Requires-Dist: nh3>=0.3.2
Requires-Dist: pygments>=2.19.2
Requires-Dist: python-multipart>=0.0.20
Requires-Dist: rich>=14.2.0
Requires-Dist: selectolax>=0.4.6
Requires-Dist: typer>=0.19.1
Requires-Dist: uvicorn>=0.34.0
Requires-Dist: fastapi[standard]>=0.119.1 ; extra == 'standard'
Maintainer: pygarap
Maintainer-email: pygarap <pygarap@gmail.com>
Requires-Python: >=3.13, <3.15
Project-URL: Changelog, https://github.com/feldroy/air/blob/main/CHANGELOG.md
Project-URL: Docs, https://feldroy.github.io/air/
Project-URL: Homepage, https://github.com/feldroy/air
Project-URL: Issues, https://github.com/feldroy/air/issues
Project-URL: Repository, https://github.com/feldroy/air
Project-URL: Sponsor, https://github.com/sponsors/feldroy
Provides-Extra: standard
